apigw_manager/__init__.py
apigw_manager/apigw/__init__.py
apigw_manager/apigw/admin.py
apigw_manager/apigw/apps.py
apigw_manager/apigw/authentication.py
apigw_manager/apigw/command.py
apigw_manager/apigw/decorators.py
apigw_manager/apigw/helper.py
apigw_manager/apigw/k8s_helper.py
apigw_manager/apigw/management/__init__.py
apigw_manager/apigw/management/commands/__init__.py
apigw_manager/apigw/management/commands/add_related_apps.py
apigw_manager/apigw/management/commands/apply_apigw_permissions.py
apigw_manager/apigw/management/commands/create_version_and_release_apigw.py
apigw_manager/apigw/management/commands/fetch_apigw_public_key.py
apigw_manager/apigw/management/commands/fetch_esb_public_key.py
apigw_manager/apigw/management/commands/grant_apigw_permissions.py
apigw_manager/apigw/management/commands/sync_apigw_config.py
apigw_manager/apigw/management/commands/sync_apigw_resources.py
apigw_manager/apigw/management/commands/sync_apigw_stage.py
apigw_manager/apigw/management/commands/sync_apigw_stage_mcp_servers.py
apigw_manager/apigw/management/commands/sync_apigw_strategies.py
apigw_manager/apigw/management/commands/sync_resource_docs_by_archive.py
apigw_manager/apigw/migrations/0001_initial.py
apigw_manager/apigw/migrations/__init__.py
apigw_manager/apigw/models.py
apigw_manager/apigw/providers.py
apigw_manager/apigw/utils.py
apigw_manager/apigw/views.py
apigw_manager/core/__init__.py
apigw_manager/core/configuration.py
apigw_manager/core/exceptions.py
apigw_manager/core/fetch.py
apigw_manager/core/handler.py
apigw_manager/core/permission.py
apigw_manager/core/release.py
apigw_manager/core/sync.py
apigw_manager/core/utils.py
apigw_manager/drf/__init__.py
apigw_manager/drf/apps.py
apigw_manager/drf/authentication.py
apigw_manager/drf/management/commands/data/definition.yaml
apigw_manager/drf/management/commands/generate_definition_yaml.py
apigw_manager/drf/management/commands/generate_resources_yaml.py
apigw_manager-4.2.1.dist-info/METADATA
apigw_manager-4.2.1.dist-info/WHEEL
apigw_manager-4.2.1.dist-info/RECORD
