Metadata-Version: 2.4
Name: apigw-manager
Version: 4.2.1
Summary: The SDK for managing blueking gateway resource.
License-Expression: MIT
Author: blueking
Author-email: blueking@tencent.com
Requires-Python: >=3.8,<3.13
Classifier: License :: OSI Approved :: MIT License
Classifier: Programming Language :: Python :: 3
Classifier: Programming Language :: Python :: 3.8
Classifier: Programming Language :: Python :: 3.9
Classifier: Programming Language :: Python :: 3.10
Classifier: Programming Language :: Python :: 3.11
Classifier: Programming Language :: Python :: 3.12
Provides-Extra: cryptography
Provides-Extra: demo
Provides-Extra: django
Provides-Extra: drf
Provides-Extra: kubernetes
Requires-Dist: PyMySQL (>=1.0.2,<2.0.0) ; extra == "demo"
Requires-Dist: bkapi-bk-apigateway (>=1.0.12,<2.0.0)
Requires-Dist: bkapi-client-core (>=1.2.0)
Requires-Dist: cryptography (>=3.1.1) ; extra == "cryptography"
Requires-Dist: cryptography ; extra == "drf"
Requires-Dist: django ; extra == "demo"
Requires-Dist: django ; extra == "django"
Requires-Dist: django ; extra == "drf"
Requires-Dist: django-environ (>=0.8.1) ; extra == "demo"
Requires-Dist: djangorestframework (>=3.10.3) ; extra == "drf"
Requires-Dist: docutils (==0.20.1)
Requires-Dist: drf-spectacular (<=0.27.2) ; extra == "drf"
Requires-Dist: kubernetes ; extra == "kubernetes"
Requires-Dist: packaging (>=20.4)
Requires-Dist: pyjwt (>=2.0.0) ; extra == "cryptography"
Requires-Dist: pyjwt ; extra == "demo"
Requires-Dist: pyjwt ; extra == "django"
Requires-Dist: pyjwt ; extra == "drf"
Requires-Dist: pyyaml (>=5.4.2)
Requires-Dist: setuptools (>=21.0.0)
Requires-Dist: urllib3 (>=1.25.3)
Project-URL: Homepage, https://github.com/TencentBlueKing/bkpaas-python-sdk/
Project-URL: Repository, https://github.com/TencentBlueKing/bkpaas-python-sdk/
